wordmarker/__init__.py
wordmarker/contexts/__init__.py
wordmarker/contexts/application_context.py
wordmarker/contexts/context.py
wordmarker/contexts/system_context.py
wordmarker/contexts/yaml_context.py
wordmarker/creatives/__init__.py
wordmarker/creatives/builder.py
wordmarker/creatives/factory.py
wordmarker/data/__init__.py
wordmarker/data/formatter.py
wordmarker/data/resource.py
wordmarker/loaders/__init__.py
wordmarker/loaders/default_resource_loader.py
wordmarker/loaders/resource_loader.py
wordmarker/loaders/yaml_resource_loader.py
wordmarker/scripts/__init__.py
wordmarker/scripts/quickstart.py
wordmarker/templates/__init__.py
wordmarker/templates/csv_template.py
wordmarker/templates/pdbc_template.py
wordmarker/templates/word_template.py
wordmarker/utils/__init__.py
wordmarker/utils/file.py
wordmarker/utils/logger.py
wordmarker/utils/yaml.py
wordmarker-0.0.7.dist-info/LICENSE
wordmarker-0.0.7.dist-info/METADATA
wordmarker-0.0.7.dist-info/WHEEL
wordmarker-0.0.7.dist-info/entry_points.txt
wordmarker-0.0.7.dist-info/top_level.txt
wordmarker-0.0.7.dist-info/RECORD
